experimenter/__init__.py
experimenter-0.3.dist-info/LICENSE
experimenter-0.3.dist-info/METADATA
experimenter-0.3.dist-info/WHEEL
experimenter-0.3.dist-info/top_level.txt
experimenter-0.3.dist-info/RECORD
